relationalai/snowflake_sdk/__init__.py
relationalai/snowflake_sdk/api.py
relationalai_sdk_snowflake-0.0.1.dist-info/LICENSE
relationalai_sdk_snowflake-0.0.1.dist-info/METADATA
relationalai_sdk_snowflake-0.0.1.dist-info/WHEEL
relationalai_sdk_snowflake-0.0.1.dist-info/top_level.txt
relationalai_sdk_snowflake-0.0.1.dist-info/RECORD
