Metadata-Version: 2.1
Name: relationalai-sdk-snowflake
Version: 0.0.1
Summary: The RelationalAI Software Development Kit for Snowflake Snowpark Python
Author-email: "RelationalAI, Inc." <support@relational.ai>
License: http://www.apache.org/licenses/LICENSE-2.0
Project-URL: Homepage, https://github.com/RelationalAI/rai-sdk-python/tree/main/relationalai-sdk-snowflake
Project-URL: Source, https://github.com/RelationalAI/rai-sdk-python/tree/main/relationalai-sdk-snowflake
Keywords: RelationalAI,SDK,Snowflake,Snowpark,Python
Classifier: Development Status :: 3 - Alpha
Classifier: Intended Audience :: Developers
Classifier: Intended Audience :: Information Technology
Classifier: Intended Audience :: System Administrators
Classifier: License :: OSI Approved :: Apache Software License
Classifier: Natural Language :: English
Classifier: Operating System :: OS Independent
Classifier: Programming Language :: Python :: 3 :: Only
Classifier: Programming Language :: Python :: 3.10
Classifier: Programming Language :: Python :: 3.11
Classifier: Programming Language :: Python :: 3.12
Classifier: Programming Language :: Python :: 3.8
Classifier: Programming Language :: Python :: 3.9
Classifier: Programming Language :: Python :: 3
Classifier: Topic :: Database
Classifier: Topic :: Scientific/Engineering :: Information Analysis
Classifier: Topic :: Software Development :: Libraries :: Application Frameworks
Classifier: Topic :: Software Development :: Libraries :: Python Modules
Classifier: Topic :: Software Development :: Libraries
Classifier: Topic :: Software Development
Requires-Python: >=3.8
License-File: LICENSE
Requires-Dist: snowflake-snowpark-python
